AUTHORS
LICENSE
MANIFEST.in
README.rst
setup.cfg
setup.py
Django_Multiple_Include.egg-info/PKG-INFO
Django_Multiple_Include.egg-info/SOURCES.txt
Django_Multiple_Include.egg-info/dependency_links.txt
Django_Multiple_Include.egg-info/top_level.txt
django_multiple_include.egg-info/SOURCES.txt
multiple_include/__init__.py
multiple_include/models.py
multiple_include/templatetags/__init__.py
multiple_include/templatetags/multiple_include.py
multiple_include/tests/__init__.py
multiple_include/tests/local_settings.py
multiple_include/tests/models.py
multiple_include/tests/settings.py
multiple_include/tests/urls.py