Metadata-Version: 1.1
Name: django-multiple-include
Version: 0.0.1
Summary: A version of ``{% include %}`` that accepts multiple template names.
Home-page: https://github.com/fcurella/django-multiple-include
Author: Flavio Curella
Author-email: flavio.curella@gmail.com
License: MIT
Platform: UNKNOWN
Classifier: Development Status :: 3 - Alpha
Classifier: Environment :: Console
Classifier: Intended Audience :: Developers
Classifier: Intended Audience :: Information Technology
Classifier: License :: OSI Approved :: MIT License
Classifier: Operating System :: OS Independent
Classifier: Programming Language :: Python
Classifier: Framework :: Django
